{
    "configs":[
        {
            "server":"jp5.cdd3.com",
            "server_port":"19507",
            "password":"dF98sa",
            "method":"aes-256-cfb",
            "remarks":"\u65e5\u672c\u4e1c\u4eac\u9ad8\u901f\u7ebf\u8def\u4e94\u7ec4"
        },
        {
            "server":"jp1.cdd3.com",
            "server_port":"19507",
            "password":"dF98sa",
            "method":"aes-256-cfb",
            "remarks":"\u65e5\u672c\u4e1c\u4eac\u9ad8\u901f\u7ebf\u8def\u4e00\u7ec4"
        },
        {
            "server":"jp2.cdd3.com",
            "server_port":"19507",
            "password":"dF98sa",
            "method":"aes-256-cfb",
            "remarks":"\u65e5\u672c\u4e1c\u4eac\u9ad8\u901f\u7ebf\u8def\u4e8c\u7ec4"
        },
        {
            "server":"jp3.cdd3.com",
            "server_port":"19507",
            "password":"dF98sa",
            "method":"aes-256-cfb",
            "remarks":"\u65e5\u672c\u4e1c\u4eac\u9ad8\u901f\u7ebf\u8def\u4e09\u7ec4"
        },
        {
            "server":"jp11.cdd3.com",
            "server_port":"19507",
            "password":"dF98sa",
            "method":"aes-256-cfb",
            "remarks":"\u65e5\u672c\u4e1c\u4eac\u9ad8\u901f\u7ebf\u8def\u5341\u4e00\u7ec4"
        },
        {
            "server":"jp6.cdd3.com",
            "server_port":"19507",
            "password":"dF98sa",
            "method":"aes-256-cfb",
            "remarks":"\u65e5\u672c\u4e1c\u4eac\u9ad8\u901f\u7ebf\u8def\u516d\u7ec4"
        },
        {
            "server":"jp7.cdd3.com",
            "server_port":"19507",
            "password":"dF98sa",
            "method":"aes-256-cfb",
            "remarks":"\u65e5\u672c\u4e1c\u4eac\u9ad8\u901f\u7ebf\u8def\u4e03\u7ec4"
        },
        {
            "server":"jp8.cdd3.com",
            "server_port":"19507",
            "password":"dF98sa",
            "method":"aes-256-cfb",
            "remarks":"\u65e5\u672c\u4e1c\u4eac\u9ad8\u901f\u7ebf\u8def\u516b\u7ec4"
        },
        {
            "server":"jp9.cdd3.com",
            "server_port":"19507",
            "password":"dF98sa",
            "method":"aes-256-cfb",
            "remarks":"\u65e5\u672c\u4e1c\u4eac\u9ad8\u901f\u7ebf\u8def\u4e5d\u7ec4"
        },
        {
            "server":"jp10.cdd3.com",
            "server_port":"19507",
            "password":"dF98sa",
            "method":"aes-256-cfb",
            "remarks":"\u65e5\u672c\u4e1c\u4eac\u9ad8\u901f\u7ebf\u8def\u5341\u7ec4"
        },
        {
            "server":"jp4.cdd3.com",
            "server_port":"19507",
            "password":"dF98sa",
            "method":"aes-256-cfb",
            "remarks":"\u65e5\u672c\u4e1c\u4eac\u9ad8\u901f\u7ebf\u8def\u56db\u7ec4"
        },
        {
            "server":"jp12.cdd3.com",
            "server_port":"19507",
            "password":"dF98sa",
            "method":"aes-256-cfb",
            "remarks":"\u65e5\u672c\u4e1c\u4eac\u9ad8\u901f\u7ebf\u8def\u5341\u4e8c\u7ec4"
        },
        {
            "server":"jp13.cdd3.com",
            "server_port":"19507",
            "password":"dF98sa",
            "method":"aes-256-cfb",
            "remarks":"\u65e5\u672c\u4e1c\u4eac\u9ad8\u901f\u7ebf\u8def\u5341\u4e09\u7ec4"
        },
        {
            "server":"jp14.cdd3.com",
            "server_port":"19507",
            "password":"dF98sa",
            "method":"aes-256-cfb",
            "remarks":"\u65e5\u672c\u4e1c\u4eac\u9ad8\u901f\u7ebf\u8def\u5341\u56db\u7ec4"
        },
        {
            "server":"sg1.cdd3.com",
            "server_port":"19507",
            "password":"dF98sa",
            "method":"aes-256-cfb",
            "remarks":"\u65b0\u52a0\u5761\u9ad8\u901f\u7ebf\u8def\u4e00\u7ec4"
        },
        {
            "server":"tw1.cdd3.com",
            "server_port":"19507",
            "password":"dF98sa",
            "method":"aes-256-cfb",
            "remarks":"\u53f0\u6e7e\u9ad8\u901f\u7ebf\u8def\u4e00\u7ec4"
        },
        {
            "server":"us1.cdd3.com",
            "server_port":"19507",
            "password":"dF98sa",
            "method":"aes-256-cfb",
            "remarks":"\u7f8e\u56fd\u6d1b\u6749\u77f6\u9ad8\u901f\u7ebf\u8def\u4e00\u7ec4"
        },
        {
            "server":"us2.cdd3.com",
            "server_port":"19507",
            "password":"dF98sa",
            "method":"aes-256-cfb",
            "remarks":"\u7f8e\u56fd\u6d1b\u6749\u77f6\u9ad8\u901f\u7ebf\u8def\u4e8c\u7ec4"
        },
        {
            "server":"us3.cdd3.com",
            "server_port":"19507",
            "password":"dF98sa",
            "method":"aes-256-cfb",
            "remarks":"\u7f8e\u56fd\u6d1b\u6749\u77f6\u9ad8\u901f\u7ebf\u8def\u4e09\u7ec4"
        },
        {
            "server":"us4.cdd3.com",
            "server_port":"19507",
            "password":"dF98sa",
            "method":"aes-256-cfb",
            "remarks":"\u7f8e\u56fd\u6d1b\u6749\u77f6\u9ad8\u901f\u7ebf\u8def\u56db\u7ec4"
        },
        {
            "server":"us5.cdd3.com",
            "server_port":"19507",
            "password":"dF98sa",
            "method":"aes-256-cfb",
            "remarks":"\u7f8e\u56fd\u6d1b\u6749\u77f6\u9ad8\u901f\u7ebf\u8def\u4e94\u7ec4"
        },
        {
            "server":"us6.cdd3.com",
            "server_port":"19507",
            "password":"dF98sa",
            "method":"aes-256-cfb",
            "remarks":"\u7f8e\u56fd\u6d1b\u6749\u77f6\u9ad8\u901f\u7ebf\u8def\u516d\u7ec4"
        },
        {
            "server":"us7.cdd3.com",
            "server_port":"19507",
            "password":"dF98sa",
            "method":"aes-256-cfb",
            "remarks":"\u7f8e\u56fd\u6d1b\u6749\u77f6\u9ad8\u901f\u7ebf\u8def\u4e03\u7ec4"
        },
        {
            "server":"us8.cdd3.com",
            "server_port":"19507",
            "password":"dF98sa",
            "method":"aes-256-cfb",
            "remarks":"\u7f8e\u56fd\u6d1b\u6749\u77f6\u9ad8\u901f\u7ebf\u8def\u516b\u7ec4"
        },
        {
            "server":"uk1.cdd3.com",
            "server_port":"19507",
            "password":"dF98sa",
            "method":"aes-256-cfb",
            "remarks":"\u6b27\u6d32\u9ad8\u901f\u7ebf\u8def\u82f1\u56fd\u4e00\u7ec4"
        }
    ]
}